{
	"translations":{
		"Language":"اللغة",
		"Home":{
			"company_name":"اسم الشركة",
			"text1":"حلول أفضل لعملك",
			"text2":"الكشف عن قيمة موظفيك من خلال التكنولوجيا المبتكرة",
			"button_text":"البدء",
			"Key_Features":{
				"name":"الميزات الرئيسية",
				"para1":"يمكن أن تكون كيفية إدارة شركتك للموارد البشرية فردية للغاية ، ولكن هناك بعض الإمكانات والميزات الرئيسية يجب أن تبحث عن أي حل للتأكد من أن اختيارك يمكن أن ينمو ويتغير جنبًا إلى جنب مع احتياجات مؤسستك.",
				"keys":{
					"1":"إدارة معلومات الموظف",
					"2":"تعيين / ATS (نظام تتبع المتقدمين)",
					"3":"إدارة التعويضات / كشوف المرتبات"
				},
				"para2":"قدرات إدارة الموارد البشرية المتقدمة هي في متناول الشركات من جميع الأحجام التي تستخدم حلول البرمجيات كخدمة (SaaS). لا تعتبر هذه العروض أرخص من الحلول المحلية القديمة فحسب ، بل إنها أيضًا منصات برمجية بديهية ومصممة بألوان زاهية ليست سهلة الاستخدام فحسب ، بل تتكامل أيضًا بسهولة مع أدوات SaaS للمكتب الخلفي",
				"button_text":"حلول أفضل لعملك0"
			},
			"text3":"بينما يقدم كل",
			"text4":"حلول HRIS إمكانات وميزات مختلفة قليلاً",
			"text5":"لديهم جميعًا العديد من الوظائف المشتركة ، بما في ذلك ما يلي:",
			"section1":{
				"title":"تتبع المتقدمين (AT).",
				"body":"يتضمن القدرة على إدارة إعلانات الوظائف والتطبيقات وحتى الإعداد للموظفين الجدد."
			},
			"section2":{
				"title":"إدارة الفوائد.",
				"body":"أمر بالغ الأهمية لمعظم عمليات الموارد البشرية وما يقدمه صانعو برامج HRMS هنا يمكن أن يختلف من مجرد إدارة تسجيل الموظفين على طول الطريق إلى تقديم خطط مزايا محددة للعملاء."
			},
			"section3":{
				"title":"الجدولة وتخطيط التحول",
				"body":" غالبًا ما تكون أدوات مخصصة على الرغم من أن القدرة يمكن أن تظهر كجزء من منصات أكبر لنظام إدارة الموارد البشرية أو تلك التي تركز على الأعمال التجارية حيث تكون هذه القدرة مهمة."
			},
			"benifit_section":{
				"title":"فوائد نظام معلومات الموارد البشرية لدينا",
				"para1":"حلول HRIS إمكانات وميزات مختلفة قليلاً0",
				"para2":"حلول HRIS إمكانات وميزات مختلفة قليلاً1"
			},
			"action_section":{
				"para":"إذا كنت بحاجة إلى مساعدة في استخدام إدارة الموارد البشرية ، يرجى الاتصال بنا. تتوفر أرقام هواتف الدعم للعملاء المشتركين في خطة خدمة المؤسسة. اتصل بدعم اسم الشركة لطلب رقم دعم لمنطقتك.",
				"button_text":"دعوة لاتخاذ إجراء"
			},
			"contact_section":{
				"name":"جهة اتصال",
				"para":"الهدف من كل صفحة اتصل بنا هو التحويل عن طريق تقديم طريقة (طرق) الاتصال بشركة بشكل واضح وفعال في أسرع وقت ممكن.",
				"form":{
					"left":{
						"label1":"الموقع",
						"label2":"البريد الإلكتروني",
						"label3":"اتصال"
					},
					"right":{
						"name":"اسمك",
						"email":"بريدك الإلكتروني",
						"subject":"الموضوع",
						"message":"دعوة لاتخاذ إجراء0"
					},
					"button_text":"دعوة لاتخاذ إجراء1"
				}
			}
		},
		"Account":{
			"Login":"تسجيل الدخول",
			"Help":"مساعدة",
			"Logout":"تسجيل الخروج"
		},
		"buttons":{
			"Add":"إضافة",
			"Delete":"حذف",
			"Edit":"تحرير",
			"Submit":"إرسال",
			"Reset":"إعادة تعيين"
		},
		"Side_Nav":{
			"Dashboard":"لوحة التحكم",
			"Admin":{
				"name":"المسؤول",
				"Companies":"الشركات",
				"Roles":"الأدوار",
				"Privilege":"الامتياز"
			},
			"Manage_Users":{
				"name":"إدارة المستخدمين",
				"Users":"المستخدمين"
			},
			"Basic_Data":{
				"name":"البيانات الأساسية",
				"Nationality":"الجنسية",
				"Salary_Config":"لوحة التحكم0",
				"Leave_Type":"لوحة التحكم1",
				"Education_Levels":"لوحة التحكم2",
				"Employment_Types":"لوحة التحكم3",
				"Departments":"لوحة التحكم4",
				"Insurance_Providers":"لوحة التحكم5",
				"Job_Titles":"لوحة التحكم6",
				"Holiday":"لوحة التحكم7",
				"Time_Schedules":"لوحة التحكم8",
				"Branch":"لوحة التحكم9",
				"Appraisal_Questions":"المسؤول0"
			},
			"Employee":{
				"name":"المسؤول1",
				"Employee_List":"المسؤول2",
				"Employee_Profile":"المسؤول3"
			},
			"Self_Service":{
				"name":"المسؤول4",
				"Entry_Request":"المسؤول5",
				"Approve_Entry_Request":"المسؤول6"
			},
			"Leave":{
				"name":"المسؤول7",
				"Leave_List":"المسؤول8",
				"New_Leave":"المسؤول9",
				"Approve_Leave":"الشركات0"
			},
			"Loan":{
				"name":"الشركات1",
				"Loan_List":"الشركات2",
				"New_Loan":"الشركات3",
				"Approve_Loan":"الشركات4"
			},
			"Payroll":{
				"name":"الشركات5",
				"Salary_Process":"الشركات6",
				"Salary_List":"الشركات7"
			},
			"Reports":{
				"name":"الشركات8",
				"Employee":"الشركات9",
				"Company":"الأدوار0",
				"Attendance":"الأدوار1",
				"Leave":"الأدوار2",
				"Loan":"الأدوار3",
				"Salary":"الأدوار4"
			},
			"Help":{
				"name":"الأدوار5"
			}
		},
		"dashboard":{
			"Employee":"المسؤول1",
			"Present":"الأدوار6",
			"Leave":"المسؤول7",
			"Absent":"الأدوار7",
			"Holiday":"لوحة التحكم7",
			"Total_Salary":"الأدوار8"
		},
		"Admin":{
			"Companies":{
				"name":"الشركات",
				"table_headers":{
					"Code":"الرمز",
					"Name":"الاسم",
					"Email":"البريد الإلكتروني",
					"Subscription_Fee":"رسوم الاشتراك",
					"Expiry_Date":"تاريخ انتهاء الصلاحية",
					"Status":"الحالة",
					"Action":"الإجراء"
				},
				"Create":{
					"header":"إنشاء شركة جديدة",
					"Company_Code":"رمز الشركة",
					"Company_Name":"الرمز0",
					"Email":"البريد الإلكتروني",
					"Subscription":{
						"name":"الرمز1",
						"Description":"الرمز2",
						"Price":"الرمز3",
						"Expiry_Date":"تاريخ انتهاء الصلاحية"
					},
					"User":{
						"name":"الرمز4",
						"Select_Title":"الرمز5",
						"First_Name":"الرمز6",
						"Last_Name":"الرمز7",
						"Email":"لرمز8",
						"Phone":"الرمز9",
						"Select_Role":"الاسم0",
						"Select_Gender":"الاسم1",
						"Password":"الاسم2",
						"Confirm_Password":"الاسم3"
					}
				}
			},
			"Roles":{
				"name":"الأدوار",
				"table_headers":{
					"Name":"الاسم",
					"Description":"الشركات0",
					"Status":"الحالة",
					"Action":"الإجراء"
				}
			},
			"Privilege":{
				"name":"الشركات1"
			}
		},
		"Manage_Users":{
			"Users":{
				"name":"المستخدمون",
				"table_headers":{
					"User_Role":"دور المستخدم",
					"Role_Name":"اسم الدور",
					"Full_Name":"الاسم الكامل",
					"Email":"البريد الإلكتروني",
					"Contact":"جهة الاتصال",
					"Status":"الحالة"
				},
				"Create":{
					"header":"إنشاء مستخدم جديد",
					"User_ID":"معرف المستخدم",
					"ID_placeholder":"أدخل معرف مستخدم جديد",
					"Check":"دور المستخدم0",
					"Password":"دور المستخدم1",
					"Password_Placeholder":"دور المستخدم2",
					"Select_Title":"دور المستخدم3",
					"First_Name":"دور المستخدم4",
					"First_Name_Placeholder":"دور المستخدم5",
					"Last_Name":"دور المستخدم6",
					"Last_Name_Placeholder":"دور المستخدم7",
					"Email":"البريد الإلكتروني",
					"Email_Placeholder":"دور المستخدم8",
					"Select_Role":"دور المستخدم9",
					"Select_Gender":"اسم الدور0",
					"Phone":"اسم الدور1",
					"Phone_Placeholder":"اسم الدور2"
				},
				"Edit":{
					"header":"دور المستخدم6",
					"":""
				}
			}
		},
		"Basic_Data":{
			"Nationality":{
				"name":"الجنسية",
				"table_headers":{
					"header":"قائمة نوع الجنسية",
					"Name":"الاسم",
					"Order":"الأمر",
					"Status":"الحالة"
				},
				"Create":{
					"header":"إنشاء الجنسية",
					"Name":"اسم الجنسية",
					"Name_Placeholder":"أدخل اسم الجنسية",
					"Order":"الأمر",
					"Order_Placeholder":"أدخل طلبًا"
				},
				"Edit":{
					"header":"تحرير تفاصيل الجنسية"
				}
			}
		}
	}
}